gecko_messages/__init__.py
gecko_messages/calibration_msgs_pb2.py
gecko_messages/camera_msgs_pb2.py
gecko_messages/drone_msgs_pb2.py
gecko_messages/geometry_msgs_pb2.py
gecko_messages/kinematic_msgs_pb2.py
gecko_messages/math_msgs_pb2.py
gecko_messages/sensor_msgs_pb2.py
gecko_messages/standard_msgs_pb2.py
gecko_messages/tuples.py
gecko_messages-2025.3.23.dist-info/LICENSE
gecko_messages-2025.3.23.dist-info/METADATA
gecko_messages-2025.3.23.dist-info/WHEEL
gecko_messages-2025.3.23.dist-info/RECORD
