Metadata-Version: 2.3
Name: gecko_messages
Version: 2025.3.23
Summary: gecko messages
License: MIT
Keywords: gecko,messages,robotics,protobuf,namedtuples
Author: walchko
Author-email: walchko@users.noreply.github.com
Requires-Python: >=3.10
Classifier: Development Status :: 4 - Beta
Classifier: Intended Audience :: Developers
Classifier: License :: OSI Approved :: MIT License
Classifier: Operating System :: OS Independent
Classifier: Programming Language :: Python :: 3
Classifier: Programming Language :: Python :: 3.10
Classifier: Programming Language :: Python :: 3.11
Classifier: Programming Language :: Python :: 3.12
Classifier: Programming Language :: Python :: 3.13
Classifier: Topic :: Software Development :: Libraries
Classifier: Topic :: Software Development :: Libraries :: Application Frameworks
Classifier: Topic :: Software Development :: Libraries :: Python Modules
Requires-Dist: protobuf (==5.29.3)
Project-URL: Homepage, https://pypi.org/project/gecko-messages/
Project-URL: Repository, https://github.com/gecko-robotics/messages
